Metadata-Version: 2.1
Name: bradescoPixCTS
Version: 0.2
Summary: SDK Bradesco PIX V8
Home-page: https://pypi.org/user/monetizze/
Author: Monetizze
Author-email: payments@monetizze.com.br
License: MIT License
Keywords: bradesco
